beu/__init__.py
beu/scripts/__init__.py
beu/scripts/shell.py
beu-0.1.36.dist-info/LICENSE.txt
beu-0.1.36.dist-info/METADATA
beu-0.1.36.dist-info/WHEEL
beu-0.1.36.dist-info/entry_points.txt
beu-0.1.36.dist-info/top_level.txt
beu-0.1.36.dist-info/RECORD
