Metadata-Version: 2.1
Name: beu
Version: 0.1.36
Summary: Beginner Express .:. Back End .:. Big Example .:. Brainstorm Effectively
Home-page: https://github.com/kenjyco/beu
Download-URL: https://github.com/kenjyco/beu/tarball/v0.1.36
Author: Ken
Author-email: kenjyco@gmail.com
License: MIT
Keywords: kenjyco
Platform: UNKNOWN
Classifier: Development Status :: 3 - Alpha
Classifier: Development Status :: 4 - Beta
Classifier: Environment :: Console
Classifier: Environment :: Web Environment
Classifier: Framework :: IPython
Classifier: Framework :: Pytest
Classifier: Intended Audience :: Developers
Classifier: License :: OSI Approved :: MIT License
Classifier: Operating System :: MacOS :: MacOS X
Classifier: Operating System :: POSIX :: Linux
Classifier: Programming Language :: Python
Classifier: Programming Language :: Python :: 3.5
Classifier: Programming Language :: SQL
Classifier: Programming Language :: Unix Shell
Classifier: Topic :: Database
Classifier: Topic :: Multimedia :: Sound/Audio :: Players
Classifier: Topic :: Multimedia :: Video
Classifier: Topic :: Software Development :: Libraries
Classifier: Topic :: Software Development :: Testing
Classifier: Topic :: Software Development :: Version Control :: Git
Classifier: Topic :: System :: Filesystems
Classifier: Topic :: System :: Logging
Classifier: Topic :: System :: Shells
Classifier: Topic :: Terminals
Classifier: Topic :: Text Processing :: Filters
Classifier: Topic :: Text Processing :: General
Classifier: Topic :: Text Processing :: Markup :: HTML
Classifier: Topic :: Text Processing :: Markup :: Markdown
Classifier: Topic :: Text Processing :: Markup :: XML
Classifier: Topic :: Utilities
License-File: LICENSE.txt
Requires-Dist: aws-info-helper[redis-helper]
Requires-Dist: bg-helper
Requires-Dist: chloop
Requires-Dist: click
Requires-Dist: dt-helper
Requires-Dist: easy-workflow-manager
Requires-Dist: fs-helper
Requires-Dist: input-helper[full]
Requires-Dist: jira-helper
Requires-Dist: mongo-helper
Requires-Dist: parse-helper
Requires-Dist: readme-helper
Requires-Dist: redis-helper
Requires-Dist: settings-helper
Requires-Dist: sql-helper
Requires-Dist: testing-helper
Requires-Dist: webclient-helper[bs4]
Requires-Dist: yt-helper[redis-helper]
